{
	"name": "IN301000",
	"graphName": "PX.Objects.IN.INReceiptEntry",
	"primaryView": "receipt",
	"featureInstalled": [],
	"actions": [
		{
			"name": "LineSplittingExtension_GenerateNumbers",
			"decorators": []
		},
		{
			"name": "AddInvSelBySite",
			"decorators": []
		}
	],
	"views": [
		{
			"name": "receipt",
			"dacClassName": {
				"name": "INRegister"
			},
			"displayName": "receipt",
			"isCollection": false,
			"isFullCollection": false,
			"featureInstalled": [],
			"fields": [
				{
					"args": null,
					"stateType": "default",
					"name": "RefNbr",
					"bound": true,
					"commitChanges": true,
					"suppressLabel": false,
					"readonly": false,
					"disabled": false,
					"calculated": false,
					"linkCommand": null,
					"text": null,
					"group": null,
					"placeBeforeProperty": null,
					"placeAfterProperty": null,
					"decorators": [
						{
							"name": {
								"name": "commitChanges"
							},
							"arguments": []
						}
					]
				},
				{
					"args": null,
					"stateType": "default",
					"name": "Status",
					"bound": true,
					"commitChanges": false,
					"suppressLabel": false,
					"readonly": false,
					"disabled": false,
					"calculated": false,
					"linkCommand": null,
					"text": null,
					"group": null,
					"placeBeforeProperty": null,
					"placeAfterProperty": null,
					"decorators": []
				},
				{
					"args": null,
					"stateType": "default",
					"name": "BranchID",
					"bound": true,
					"commitChanges": true,
					"suppressLabel": false,
					"readonly": false,
					"disabled": false,
					"calculated": false,
					"linkCommand": null,
					"text": null,
					"group": null,
					"placeBeforeProperty": null,
					"placeAfterProperty": null,
					"decorators": [
						{
							"name": {
								"name": "commitChanges"
							},
							"arguments": []
						}
					]
				},
				{
					"args": null,
					"stateType": "default",
					"name": "TranDate",
					"bound": true,
					"commitChanges": true,
					"suppressLabel": false,
					"readonly": false,
					"disabled": false,
					"calculated": false,
					"linkCommand": null,
					"text": null,
					"group": null,
					"placeBeforeProperty": null,
					"placeAfterProperty": null,
					"decorators": [
						{
							"name": {
								"name": "commitChanges"
							},
							"arguments": []
						}
					]
				},
				{
					"args": null,
					"stateType": "default",
					"name": "FinPeriodID",
					"bound": true,
					"commitChanges": true,
					"suppressLabel": false,
					"readonly": false,
					"disabled": false,
					"calculated": false,
					"linkCommand": null,
					"text": null,
					"group": null,
					"placeBeforeProperty": null,
					"placeAfterProperty": null,
					"decorators": [
						{
							"name": {
								"name": "commitChanges"
							},
							"arguments": []
						}
					]
				},
				{
					"args": null,
					"stateType": "default",
					"name": "TransferNbr",
					"bound": true,
					"commitChanges": true,
					"suppressLabel": false,
					"readonly": false,
					"disabled": false,
					"calculated": false,
					"linkCommand": null,
					"text": null,
					"group": null,
					"placeBeforeProperty": null,
					"placeAfterProperty": null,
					"decorators": [
						{
							"name": {
								"name": "commitChanges"
							},
							"arguments": []
						}
					]
				},
				{
					"args": null,
					"stateType": "default",
					"name": "ExtRefNbr",
					"bound": true,
					"commitChanges": false,
					"suppressLabel": false,
					"readonly": false,
					"disabled": false,
					"calculated": false,
					"linkCommand": null,
					"text": null,
					"group": null,
					"placeBeforeProperty": null,
					"placeAfterProperty": null,
					"decorators": []
				},
				{
					"args": null,
					"stateType": "default",
					"name": "TranDesc",
					"bound": true,
					"commitChanges": false,
					"suppressLabel": false,
					"readonly": false,
					"disabled": false,
					"calculated": false,
					"linkCommand": null,
					"text": null,
					"group": null,
					"placeBeforeProperty": null,
					"placeAfterProperty": null,
					"decorators": []
				},
				{
					"args": null,
					"stateType": "default",
					"name": "TotalQty",
					"bound": true,
					"commitChanges": false,
					"suppressLabel": false,
					"readonly": false,
					"disabled": false,
					"calculated": false,
					"linkCommand": null,
					"text": null,
					"group": null,
					"placeBeforeProperty": null,
					"placeAfterProperty": null,
					"decorators": []
				},
				{
					"args": null,
					"stateType": "default",
					"name": "ControlQty",
					"bound": true,
					"commitChanges": false,
					"suppressLabel": false,
					"readonly": false,
					"disabled": false,
					"calculated": false,
					"linkCommand": null,
					"text": null,
					"group": null,
					"placeBeforeProperty": null,
					"placeAfterProperty": null,
					"decorators": []
				},
				{
					"args": null,
					"stateType": "default",
					"name": "TotalCost",
					"bound": true,
					"commitChanges": false,
					"suppressLabel": false,
					"readonly": false,
					"disabled": false,
					"calculated": false,
					"linkCommand": null,
					"text": null,
					"group": null,
					"placeBeforeProperty": null,
					"placeAfterProperty": null,
					"decorators": []
				},
				{
					"args": null,
					"stateType": "default",
					"name": "ControlCost",
					"bound": true,
					"commitChanges": false,
					"suppressLabel": false,
					"readonly": false,
					"disabled": false,
					"calculated": false,
					"linkCommand": null,
					"text": null,
					"group": null,
					"placeBeforeProperty": null,
					"placeAfterProperty": null,
					"decorators": []
				},
				{
					"args": null,
					"stateType": "default",
					"name": "BatchNbr",
					"bound": true,
					"commitChanges": false,
					"suppressLabel": false,
					"readonly": false,
					"disabled": false,
					"calculated": false,
					"linkCommand": null,
					"text": null,
					"group": null,
					"placeBeforeProperty": null,
					"placeAfterProperty": null,
					"decorators": []
				},
				{
					"args": null,
					"stateType": "default",
					"name": "BranchBaseCuryID",
					"bound": true,
					"commitChanges": false,
					"suppressLabel": false,
					"readonly": false,
					"disabled": false,
					"calculated": false,
					"linkCommand": null,
					"text": null,
					"group": null,
					"placeBeforeProperty": null,
					"placeAfterProperty": null,
					"decorators": []
				},
				{
					"args": null,
					"stateType": "default",
					"name": "AMBatNbr",
					"bound": true,
					"commitChanges": false,
					"suppressLabel": false,
					"readonly": false,
					"disabled": false,
					"calculated": false,
					"linkCommand": null,
					"text": null,
					"group": null,
					"placeBeforeProperty": null,
					"placeAfterProperty": null,
					"decorators": []
				},
				{
					"args": null,
					"stateType": "default",
					"name": "AMDocType",
					"bound": true,
					"commitChanges": false,
					"suppressLabel": false,
					"readonly": false,
					"disabled": false,
					"calculated": false,
					"linkCommand": null,
					"text": null,
					"group": null,
					"placeBeforeProperty": null,
					"placeAfterProperty": null,
					"decorators": []
				}
			],
			"extensions": [],
			"decorators": [],
			"actions": []
		},
		{
			"name": "CurrentDocument",
			"dacClassName": {
				"name": "INRegister"
			},
			"displayName": "CurrentDocument",
			"isCollection": false,
			"isFullCollection": false,
			"featureInstalled": [],
			"fields": [
				{
					"args": null,
					"stateType": "default",
					"name": "RefNbr",
					"bound": true,
					"commitChanges": true,
					"suppressLabel": false,
					"readonly": false,
					"disabled": false,
					"calculated": false,
					"linkCommand": null,
					"text": null,
					"group": null,
					"placeBeforeProperty": null,
					"placeAfterProperty": null,
					"decorators": [
						{
							"name": {
								"name": "commitChanges"
							},
							"arguments": []
						}
					]
				},
				{
					"args": null,
					"stateType": "default",
					"name": "Status",
					"bound": true,
					"commitChanges": false,
					"suppressLabel": false,
					"readonly": false,
					"disabled": false,
					"calculated": false,
					"linkCommand": null,
					"text": null,
					"group": null,
					"placeBeforeProperty": null,
					"placeAfterProperty": null,
					"decorators": []
				},
				{
					"args": null,
					"stateType": "default",
					"name": "BranchID",
					"bound": true,
					"commitChanges": true,
					"suppressLabel": false,
					"readonly": false,
					"disabled": false,
					"calculated": false,
					"linkCommand": null,
					"text": null,
					"group": null,
					"placeBeforeProperty": null,
					"placeAfterProperty": null,
					"decorators": [
						{
							"name": {
								"name": "commitChanges"
							},
							"arguments": []
						}
					]
				},
				{
					"args": null,
					"stateType": "default",
					"name": "TranDate",
					"bound": true,
					"commitChanges": true,
					"suppressLabel": false,
					"readonly": false,
					"disabled": false,
					"calculated": false,
					"linkCommand": null,
					"text": null,
					"group": null,
					"placeBeforeProperty": null,
					"placeAfterProperty": null,
					"decorators": [
						{
							"name": {
								"name": "commitChanges"
							},
							"arguments": []
						}
					]
				},
				{
					"args": null,
					"stateType": "default",
					"name": "FinPeriodID",
					"bound": true,
					"commitChanges": true,
					"suppressLabel": false,
					"readonly": false,
					"disabled": false,
					"calculated": false,
					"linkCommand": null,
					"text": null,
					"group": null,
					"placeBeforeProperty": null,
					"placeAfterProperty": null,
					"decorators": [
						{
							"name": {
								"name": "commitChanges"
							},
							"arguments": []
						}
					]
				},
				{
					"args": null,
					"stateType": "default",
					"name": "TransferNbr",
					"bound": true,
					"commitChanges": true,
					"suppressLabel": false,
					"readonly": false,
					"disabled": false,
					"calculated": false,
					"linkCommand": null,
					"text": null,
					"group": null,
					"placeBeforeProperty": null,
					"placeAfterProperty": null,
					"decorators": [
						{
							"name": {
								"name": "commitChanges"
							},
							"arguments": []
						}
					]
				},
				{
					"args": null,
					"stateType": "default",
					"name": "ExtRefNbr",
					"bound": true,
					"commitChanges": false,
					"suppressLabel": false,
					"readonly": false,
					"disabled": false,
					"calculated": false,
					"linkCommand": null,
					"text": null,
					"group": null,
					"placeBeforeProperty": null,
					"placeAfterProperty": null,
					"decorators": []
				},
				{
					"args": null,
					"stateType": "default",
					"name": "TranDesc",
					"bound": true,
					"commitChanges": false,
					"suppressLabel": false,
					"readonly": false,
					"disabled": false,
					"calculated": false,
					"linkCommand": null,
					"text": null,
					"group": null,
					"placeBeforeProperty": null,
					"placeAfterProperty": null,
					"decorators": []
				},
				{
					"args": null,
					"stateType": "default",
					"name": "TotalQty",
					"bound": true,
					"commitChanges": false,
					"suppressLabel": false,
					"readonly": false,
					"disabled": false,
					"calculated": false,
					"linkCommand": null,
					"text": null,
					"group": null,
					"placeBeforeProperty": null,
					"placeAfterProperty": null,
					"decorators": []
				},
				{
					"args": null,
					"stateType": "default",
					"name": "ControlQty",
					"bound": true,
					"commitChanges": false,
					"suppressLabel": false,
					"readonly": false,
					"disabled": false,
					"calculated": false,
					"linkCommand": null,
					"text": null,
					"group": null,
					"placeBeforeProperty": null,
					"placeAfterProperty": null,
					"decorators": []
				},
				{
					"args": null,
					"stateType": "default",
					"name": "TotalCost",
					"bound": true,
					"commitChanges": false,
					"suppressLabel": false,
					"readonly": false,
					"disabled": false,
					"calculated": false,
					"linkCommand": null,
					"text": null,
					"group": null,
					"placeBeforeProperty": null,
					"placeAfterProperty": null,
					"decorators": []
				},
				{
					"args": null,
					"stateType": "default",
					"name": "ControlCost",
					"bound": true,
					"commitChanges": false,
					"suppressLabel": false,
					"readonly": false,
					"disabled": false,
					"calculated": false,
					"linkCommand": null,
					"text": null,
					"group": null,
					"placeBeforeProperty": null,
					"placeAfterProperty": null,
					"decorators": []
				},
				{
					"args": null,
					"stateType": "default",
					"name": "BatchNbr",
					"bound": true,
					"commitChanges": false,
					"suppressLabel": false,
					"readonly": false,
					"disabled": false,
					"calculated": false,
					"linkCommand": null,
					"text": null,
					"group": null,
					"placeBeforeProperty": null,
					"placeAfterProperty": null,
					"decorators": []
				},
				{
					"args": null,
					"stateType": "default",
					"name": "BranchBaseCuryID",
					"bound": true,
					"commitChanges": false,
					"suppressLabel": false,
					"readonly": false,
					"disabled": false,
					"calculated": false,
					"linkCommand": null,
					"text": null,
					"group": null,
					"placeBeforeProperty": null,
					"placeAfterProperty": null,
					"decorators": []
				},
				{
					"args": null,
					"stateType": "default",
					"name": "AMBatNbr",
					"bound": true,
					"commitChanges": false,
					"suppressLabel": false,
					"readonly": false,
					"disabled": false,
					"calculated": false,
					"linkCommand": null,
					"text": null,
					"group": null,
					"placeBeforeProperty": null,
					"placeAfterProperty": null,
					"decorators": []
				},
				{
					"args": null,
					"stateType": "default",
					"name": "AMDocType",
					"bound": true,
					"commitChanges": false,
					"suppressLabel": false,
					"readonly": false,
					"disabled": false,
					"calculated": false,
					"linkCommand": null,
					"text": null,
					"group": null,
					"placeBeforeProperty": null,
					"placeAfterProperty": null,
					"decorators": []
				}
			],
			"extensions": [],
			"decorators": [],
			"actions": []
		},
		{
			"name": "transactions",
			"dacClassName": {
				"name": "INTran"
			},
			"displayName": "transactions",
			"isCollection": true,
			"isFullCollection": false,
			"featureInstalled": [],
			"fields": [
				{
					"args": null,
					"stateType": "default",
					"name": "BranchID",
					"bound": true,
					"commitChanges": true,
					"suppressLabel": false,
					"readonly": false,
					"disabled": false,
					"calculated": false,
					"linkCommand": null,
					"text": null,
					"group": null,
					"placeBeforeProperty": null,
					"placeAfterProperty": null,
					"decorators": [
						{
							"name": {
								"name": "commitChanges"
							},
							"arguments": []
						}
					]
				},
				{
					"args": null,
					"stateType": "default",
					"name": "InventoryID",
					"bound": true,
					"commitChanges": true,
					"suppressLabel": false,
					"readonly": false,
					"disabled": false,
					"calculated": false,
					"linkCommand": null,
					"text": null,
					"group": null,
					"placeBeforeProperty": null,
					"placeAfterProperty": null,
					"decorators": [
						{
							"name": {
								"name": "commitChanges"
							},
							"arguments": []
						}
					]
				},
				{
					"args": null,
					"stateType": "default",
					"name": "SubItemID",
					"bound": true,
					"commitChanges": false,
					"suppressLabel": false,
					"readonly": false,
					"disabled": false,
					"calculated": false,
					"linkCommand": null,
					"text": null,
					"group": null,
					"placeBeforeProperty": null,
					"placeAfterProperty": null,
					"decorators": []
				},
				{
					"args": null,
					"stateType": "default",
					"name": "SiteID",
					"bound": true,
					"commitChanges": true,
					"suppressLabel": false,
					"readonly": false,
					"disabled": false,
					"calculated": false,
					"linkCommand": null,
					"text": null,
					"group": null,
					"placeBeforeProperty": null,
					"placeAfterProperty": null,
					"decorators": [
						{
							"name": {
								"name": "commitChanges"
							},
							"arguments": []
						}
					]
				},
				{
					"args": null,
					"stateType": "default",
					"name": "LocationID",
					"bound": true,
					"commitChanges": true,
					"suppressLabel": false,
					"readonly": false,
					"disabled": false,
					"calculated": false,
					"linkCommand": null,
					"text": null,
					"group": null,
					"placeBeforeProperty": null,
					"placeAfterProperty": null,
					"decorators": [
						{
							"name": {
								"name": "commitChanges"
							},
							"arguments": []
						}
					]
				},
				{
					"args": null,
					"stateType": "default",
					"name": "Qty",
					"bound": true,
					"commitChanges": false,
					"suppressLabel": false,
					"readonly": false,
					"disabled": false,
					"calculated": false,
					"linkCommand": null,
					"text": null,
					"group": null,
					"placeBeforeProperty": null,
					"placeAfterProperty": null,
					"decorators": []
				},
				{
					"args": null,
					"stateType": "default",
					"name": "UOM",
					"bound": true,
					"commitChanges": true,
					"suppressLabel": false,
					"readonly": false,
					"disabled": false,
					"calculated": false,
					"linkCommand": null,
					"text": null,
					"group": null,
					"placeBeforeProperty": null,
					"placeAfterProperty": null,
					"decorators": [
						{
							"name": {
								"name": "commitChanges"
							},
							"arguments": []
						}
					]
				},
				{
					"args": null,
					"stateType": "default",
					"name": "UnitCost",
					"bound": true,
					"commitChanges": false,
					"suppressLabel": false,
					"readonly": false,
					"disabled": false,
					"calculated": false,
					"linkCommand": null,
					"text": null,
					"group": null,
					"placeBeforeProperty": null,
					"placeAfterProperty": null,
					"decorators": []
				},
				{
					"args": null,
					"stateType": "default",
					"name": "TranCost",
					"bound": true,
					"commitChanges": false,
					"suppressLabel": false,
					"readonly": false,
					"disabled": false,
					"calculated": false,
					"linkCommand": null,
					"text": null,
					"group": null,
					"placeBeforeProperty": null,
					"placeAfterProperty": null,
					"decorators": []
				},
				{
					"args": null,
					"stateType": "default",
					"name": "LotSerialNbr",
					"bound": true,
					"commitChanges": true,
					"suppressLabel": false,
					"readonly": false,
					"disabled": false,
					"calculated": false,
					"linkCommand": null,
					"text": null,
					"group": null,
					"placeBeforeProperty": null,
					"placeAfterProperty": null,
					"decorators": [
						{
							"name": {
								"name": "commitChanges"
							},
							"arguments": []
						}
					]
				},
				{
					"args": null,
					"stateType": "default",
					"name": "ExpireDate",
					"bound": true,
					"commitChanges": false,
					"suppressLabel": false,
					"readonly": false,
					"disabled": false,
					"calculated": false,
					"linkCommand": null,
					"text": null,
					"group": null,
					"placeBeforeProperty": null,
					"placeAfterProperty": null,
					"decorators": []
				},
				{
					"args": null,
					"stateType": "default",
					"name": "ReasonCode",
					"bound": true,
					"commitChanges": true,
					"suppressLabel": false,
					"readonly": false,
					"disabled": false,
					"calculated": false,
					"linkCommand": null,
					"text": null,
					"group": null,
					"placeBeforeProperty": null,
					"placeAfterProperty": null,
					"decorators": [
						{
							"name": {
								"name": "commitChanges"
							},
							"arguments": []
						}
					]
				},
				{
					"args": null,
					"stateType": "default",
					"name": "CostLayerType",
					"bound": true,
					"commitChanges": false,
					"suppressLabel": false,
					"readonly": false,
					"disabled": false,
					"calculated": false,
					"linkCommand": null,
					"text": null,
					"group": null,
					"placeBeforeProperty": null,
					"placeAfterProperty": null,
					"decorators": []
				},
				{
					"args": null,
					"stateType": "default",
					"name": "SpecialOrderCostCenterID",
					"bound": true,
					"commitChanges": false,
					"suppressLabel": false,
					"readonly": false,
					"disabled": false,
					"calculated": false,
					"linkCommand": null,
					"text": null,
					"group": null,
					"placeBeforeProperty": null,
					"placeAfterProperty": null,
					"decorators": []
				},
				{
					"args": null,
					"stateType": "default",
					"name": "ProjectID",
					"bound": true,
					"commitChanges": true,
					"suppressLabel": false,
					"readonly": false,
					"disabled": false,
					"calculated": false,
					"linkCommand": null,
					"text": null,
					"group": null,
					"placeBeforeProperty": null,
					"placeAfterProperty": null,
					"decorators": [
						{
							"name": {
								"name": "commitChanges"
							},
							"arguments": []
						}
					]
				},
				{
					"args": null,
					"stateType": "default",
					"name": "TaskID",
					"bound": true,
					"commitChanges": true,
					"suppressLabel": false,
					"readonly": false,
					"disabled": false,
					"calculated": false,
					"linkCommand": null,
					"text": null,
					"group": null,
					"placeBeforeProperty": null,
					"placeAfterProperty": null,
					"decorators": [
						{
							"name": {
								"name": "commitChanges"
							},
							"arguments": []
						}
					]
				},
				{
					"args": null,
					"stateType": "default",
					"name": "CostCodeID",
					"bound": true,
					"commitChanges": true,
					"suppressLabel": false,
					"readonly": false,
					"disabled": false,
					"calculated": false,
					"linkCommand": null,
					"text": null,
					"group": null,
					"placeBeforeProperty": null,
					"placeAfterProperty": null,
					"decorators": [
						{
							"name": {
								"name": "commitChanges"
							},
							"arguments": []
						}
					]
				},
				{
					"args": null,
					"stateType": "default",
					"name": "TranDesc",
					"bound": true,
					"commitChanges": false,
					"suppressLabel": false,
					"readonly": false,
					"disabled": false,
					"calculated": false,
					"linkCommand": null,
					"text": null,
					"group": null,
					"placeBeforeProperty": null,
					"placeAfterProperty": null,
					"decorators": []
				},
				{
					"args": null,
					"stateType": "default",
					"name": "POReceiptType",
					"bound": true,
					"commitChanges": false,
					"suppressLabel": false,
					"readonly": false,
					"disabled": false,
					"calculated": false,
					"linkCommand": null,
					"text": null,
					"group": null,
					"placeBeforeProperty": null,
					"placeAfterProperty": null,
					"decorators": []
				},
				{
					"args": null,
					"stateType": "default",
					"name": "POReceiptNbr",
					"bound": true,
					"commitChanges": false,
					"suppressLabel": false,
					"readonly": false,
					"disabled": false,
					"calculated": false,
					"linkCommand": null,
					"text": null,
					"group": null,
					"placeBeforeProperty": null,
					"placeAfterProperty": null,
					"decorators": []
				}
			],
			"extensions": [],
			"decorators": [],
			"actions": [
				{
					"name": "LineSplittingExtension_ShowSplits",
					"decorators": []
				},
				{
					"name": "AddInvBySite",
					"decorators": []
				}
			]
		},
		{
			"name": "LineSplittingExtension_LotSerOptions",
			"dacClassName": {
				"name": "LineSplittingHeader"
			},
			"displayName": "LineSplittingExtension_LotSerOptions",
			"isCollection": false,
			"isFullCollection": false,
			"featureInstalled": [],
			"fields": [
				{
					"args": null,
					"stateType": "default",
					"name": "UnassignedQty",
					"bound": true,
					"commitChanges": true,
					"suppressLabel": false,
					"readonly": false,
					"disabled": false,
					"calculated": false,
					"linkCommand": null,
					"text": null,
					"group": null,
					"placeBeforeProperty": null,
					"placeAfterProperty": null,
					"decorators": [
						{
							"name": {
								"name": "commitChanges"
							},
							"arguments": []
						}
					]
				},
				{
					"args": null,
					"stateType": "default",
					"name": "Qty",
					"bound": true,
					"commitChanges": true,
					"suppressLabel": false,
					"readonly": false,
					"disabled": false,
					"calculated": false,
					"linkCommand": null,
					"text": null,
					"group": null,
					"placeBeforeProperty": null,
					"placeAfterProperty": null,
					"decorators": [
						{
							"name": {
								"name": "commitChanges"
							},
							"arguments": []
						}
					]
				},
				{
					"args": null,
					"stateType": "default",
					"name": "StartNumVal",
					"bound": true,
					"commitChanges": true,
					"suppressLabel": false,
					"readonly": false,
					"disabled": false,
					"calculated": false,
					"linkCommand": null,
					"text": null,
					"group": null,
					"placeBeforeProperty": null,
					"placeAfterProperty": null,
					"decorators": [
						{
							"name": {
								"name": "commitChanges"
							},
							"arguments": []
						}
					]
				}
			],
			"extensions": [],
			"decorators": [],
			"actions": []
		},
		{
			"name": "splits",
			"dacClassName": {
				"name": "INTranSplit"
			},
			"displayName": "splits",
			"isCollection": true,
			"isFullCollection": false,
			"featureInstalled": [],
			"fields": [
				{
					"args": null,
					"stateType": "default",
					"name": "InventoryID",
					"bound": true,
					"commitChanges": false,
					"suppressLabel": false,
					"readonly": false,
					"disabled": false,
					"calculated": false,
					"linkCommand": null,
					"text": null,
					"group": null,
					"placeBeforeProperty": null,
					"placeAfterProperty": null,
					"decorators": []
				},
				{
					"args": null,
					"stateType": "default",
					"name": "SubItemID",
					"bound": true,
					"commitChanges": false,
					"suppressLabel": false,
					"readonly": false,
					"disabled": false,
					"calculated": false,
					"linkCommand": null,
					"text": null,
					"group": null,
					"placeBeforeProperty": null,
					"placeAfterProperty": null,
					"decorators": []
				},
				{
					"args": null,
					"stateType": "default",
					"name": "LocationID",
					"bound": true,
					"commitChanges": false,
					"suppressLabel": false,
					"readonly": false,
					"disabled": false,
					"calculated": false,
					"linkCommand": null,
					"text": null,
					"group": null,
					"placeBeforeProperty": null,
					"placeAfterProperty": null,
					"decorators": []
				},
				{
					"args": null,
					"stateType": "default",
					"name": "LotSerialNbr",
					"bound": true,
					"commitChanges": false,
					"suppressLabel": false,
					"readonly": false,
					"disabled": false,
					"calculated": false,
					"linkCommand": null,
					"text": null,
					"group": null,
					"placeBeforeProperty": null,
					"placeAfterProperty": null,
					"decorators": []
				},
				{
					"args": null,
					"stateType": "default",
					"name": "Qty",
					"bound": true,
					"commitChanges": false,
					"suppressLabel": false,
					"readonly": false,
					"disabled": false,
					"calculated": false,
					"linkCommand": null,
					"text": null,
					"group": null,
					"placeBeforeProperty": null,
					"placeAfterProperty": null,
					"decorators": []
				},
				{
					"args": null,
					"stateType": "default",
					"name": "UOM",
					"bound": true,
					"commitChanges": false,
					"suppressLabel": false,
					"readonly": false,
					"disabled": false,
					"calculated": false,
					"linkCommand": null,
					"text": null,
					"group": null,
					"placeBeforeProperty": null,
					"placeAfterProperty": null,
					"decorators": []
				},
				{
					"args": null,
					"stateType": "default",
					"name": "ExpireDate",
					"bound": true,
					"commitChanges": false,
					"suppressLabel": false,
					"readonly": false,
					"disabled": false,
					"calculated": false,
					"linkCommand": null,
					"text": null,
					"group": null,
					"placeBeforeProperty": null,
					"placeAfterProperty": null,
					"decorators": []
				}
			],
			"extensions": [],
			"decorators": [],
			"actions": []
		},
		{
			"name": "sitestatusfilter",
			"dacClassName": {
				"name": "INSiteStatusFilter"
			},
			"displayName": "sitestatusfilter",
			"isCollection": false,
			"isFullCollection": false,
			"featureInstalled": [],
			"fields": [
				{
					"args": null,
					"stateType": "default",
					"name": "Inventory",
					"bound": true,
					"commitChanges": true,
					"suppressLabel": false,
					"readonly": false,
					"disabled": false,
					"calculated": false,
					"linkCommand": null,
					"text": null,
					"group": null,
					"placeBeforeProperty": null,
					"placeAfterProperty": null,
					"decorators": [
						{
							"name": {
								"name": "commitChanges"
							},
							"arguments": []
						}
					]
				},
				{
					"args": null,
					"stateType": "default",
					"name": "BarCode",
					"bound": true,
					"commitChanges": true,
					"suppressLabel": false,
					"readonly": false,
					"disabled": false,
					"calculated": false,
					"linkCommand": null,
					"text": null,
					"group": null,
					"placeBeforeProperty": null,
					"placeAfterProperty": null,
					"decorators": [
						{
							"name": {
								"name": "commitChanges"
							},
							"arguments": []
						}
					]
				},
				{
					"args": null,
					"stateType": "default",
					"name": "ItemClass",
					"bound": true,
					"commitChanges": true,
					"suppressLabel": false,
					"readonly": false,
					"disabled": false,
					"calculated": false,
					"linkCommand": null,
					"text": null,
					"group": null,
					"placeBeforeProperty": null,
					"placeAfterProperty": null,
					"decorators": [
						{
							"name": {
								"name": "commitChanges"
							},
							"arguments": []
						}
					]
				},
				{
					"args": null,
					"stateType": "default",
					"name": "SubItem",
					"bound": true,
					"commitChanges": true,
					"suppressLabel": false,
					"readonly": false,
					"disabled": false,
					"calculated": false,
					"linkCommand": null,
					"text": null,
					"group": null,
					"placeBeforeProperty": null,
					"placeAfterProperty": null,
					"decorators": [
						{
							"name": {
								"name": "commitChanges"
							},
							"arguments": []
						}
					]
				},
				{
					"args": null,
					"stateType": "default",
					"name": "SiteID",
					"bound": true,
					"commitChanges": true,
					"suppressLabel": false,
					"readonly": false,
					"disabled": false,
					"calculated": false,
					"linkCommand": null,
					"text": null,
					"group": null,
					"placeBeforeProperty": null,
					"placeAfterProperty": null,
					"decorators": [
						{
							"name": {
								"name": "commitChanges"
							},
							"arguments": []
						}
					]
				},
				{
					"args": null,
					"stateType": "default",
					"name": "LocationID",
					"bound": true,
					"commitChanges": true,
					"suppressLabel": false,
					"readonly": false,
					"disabled": false,
					"calculated": false,
					"linkCommand": null,
					"text": null,
					"group": null,
					"placeBeforeProperty": null,
					"placeAfterProperty": null,
					"decorators": [
						{
							"name": {
								"name": "commitChanges"
							},
							"arguments": []
						}
					]
				},
				{
					"args": null,
					"stateType": "default",
					"name": "OnlyAvailable",
					"bound": true,
					"commitChanges": true,
					"suppressLabel": false,
					"readonly": false,
					"disabled": false,
					"calculated": false,
					"linkCommand": null,
					"text": null,
					"group": null,
					"placeBeforeProperty": null,
					"placeAfterProperty": null,
					"decorators": [
						{
							"name": {
								"name": "commitChanges"
							},
							"arguments": []
						}
					]
				}
			],
			"extensions": [],
			"decorators": [],
			"actions": []
		},
		{
			"name": "sitestatus",
			"dacClassName": {
				"name": "INSiteStatusSelected"
			},
			"displayName": "sitestatus",
			"isCollection": true,
			"isFullCollection": false,
			"featureInstalled": [],
			"fields": [
				{
					"args": null,
					"stateType": "default",
					"name": "Selected",
					"bound": true,
					"commitChanges": false,
					"suppressLabel": false,
					"readonly": false,
					"disabled": false,
					"calculated": false,
					"linkCommand": null,
					"text": null,
					"group": null,
					"placeBeforeProperty": null,
					"placeAfterProperty": null,
					"decorators": []
				},
				{
					"args": null,
					"stateType": "default",
					"name": "QtySelected",
					"bound": true,
					"commitChanges": false,
					"suppressLabel": false,
					"readonly": false,
					"disabled": false,
					"calculated": false,
					"linkCommand": null,
					"text": null,
					"group": null,
					"placeBeforeProperty": null,
					"placeAfterProperty": null,
					"decorators": []
				},
				{
					"args": null,
					"stateType": "default",
					"name": "SiteID",
					"bound": true,
					"commitChanges": false,
					"suppressLabel": false,
					"readonly": false,
					"disabled": false,
					"calculated": false,
					"linkCommand": null,
					"text": null,
					"group": null,
					"placeBeforeProperty": null,
					"placeAfterProperty": null,
					"decorators": []
				},
				{
					"args": null,
					"stateType": "default",
					"name": "LocationID",
					"bound": true,
					"commitChanges": false,
					"suppressLabel": false,
					"readonly": false,
					"disabled": false,
					"calculated": false,
					"linkCommand": null,
					"text": null,
					"group": null,
					"placeBeforeProperty": null,
					"placeAfterProperty": null,
					"decorators": []
				},
				{
					"args": null,
					"stateType": "default",
					"name": "ItemClassID",
					"bound": true,
					"commitChanges": false,
					"suppressLabel": false,
					"readonly": false,
					"disabled": false,
					"calculated": false,
					"linkCommand": null,
					"text": null,
					"group": null,
					"placeBeforeProperty": null,
					"placeAfterProperty": null,
					"decorators": []
				},
				{
					"args": null,
					"stateType": "default",
					"name": "ItemClassDescription",
					"bound": true,
					"commitChanges": false,
					"suppressLabel": false,
					"readonly": false,
					"disabled": false,
					"calculated": false,
					"linkCommand": null,
					"text": null,
					"group": null,
					"placeBeforeProperty": null,
					"placeAfterProperty": null,
					"decorators": []
				},
				{
					"args": null,
					"stateType": "default",
					"name": "PriceClassID",
					"bound": true,
					"commitChanges": false,
					"suppressLabel": false,
					"readonly": false,
					"disabled": false,
					"calculated": false,
					"linkCommand": null,
					"text": null,
					"group": null,
					"placeBeforeProperty": null,
					"placeAfterProperty": null,
					"decorators": []
				},
				{
					"args": null,
					"stateType": "default",
					"name": "PriceClassDescription",
					"bound": true,
					"commitChanges": false,
					"suppressLabel": false,
					"readonly": false,
					"disabled": false,
					"calculated": false,
					"linkCommand": null,
					"text": null,
					"group": null,
					"placeBeforeProperty": null,
					"placeAfterProperty": null,
					"decorators": []
				},
				{
					"args": null,
					"stateType": "default",
					"name": "InventoryCD",
					"bound": true,
					"commitChanges": false,
					"suppressLabel": false,
					"readonly": false,
					"disabled": false,
					"calculated": false,
					"linkCommand": null,
					"text": null,
					"group": null,
					"placeBeforeProperty": null,
					"placeAfterProperty": null,
					"decorators": []
				},
				{
					"args": null,
					"stateType": "default",
					"name": "SubItemID",
					"bound": true,
					"commitChanges": false,
					"suppressLabel": false,
					"readonly": false,
					"disabled": false,
					"calculated": false,
					"linkCommand": null,
					"text": null,
					"group": null,
					"placeBeforeProperty": null,
					"placeAfterProperty": null,
					"decorators": []
				},
				{
					"args": null,
					"stateType": "default",
					"name": "Descr",
					"bound": true,
					"commitChanges": false,
					"suppressLabel": false,
					"readonly": false,
					"disabled": false,
					"calculated": false,
					"linkCommand": null,
					"text": null,
					"group": null,
					"placeBeforeProperty": null,
					"placeAfterProperty": null,
					"decorators": []
				},
				{
					"args": null,
					"stateType": "default",
					"name": "BaseUnit",
					"bound": true,
					"commitChanges": false,
					"suppressLabel": false,
					"readonly": false,
					"disabled": false,
					"calculated": false,
					"linkCommand": null,
					"text": null,
					"group": null,
					"placeBeforeProperty": null,
					"placeAfterProperty": null,
					"decorators": []
				},
				{
					"args": null,
					"stateType": "default",
					"name": "QtyAvail",
					"bound": true,
					"commitChanges": false,
					"suppressLabel": false,
					"readonly": false,
					"disabled": false,
					"calculated": false,
					"linkCommand": null,
					"text": null,
					"group": null,
					"placeBeforeProperty": null,
					"placeAfterProperty": null,
					"decorators": []
				},
				{
					"args": null,
					"stateType": "default",
					"name": "QtyOnHand",
					"bound": true,
					"commitChanges": false,
					"suppressLabel": false,
					"readonly": false,
					"disabled": false,
					"calculated": false,
					"linkCommand": null,
					"text": null,
					"group": null,
					"placeBeforeProperty": null,
					"placeAfterProperty": null,
					"decorators": []
				}
			],
			"extensions": [],
			"decorators": [],
			"actions": []
		}
	],
	"extensions": [],
	"decorators": [
		{
			"name": {
				"name": "graphInfo"
			},
			"arguments": [
				{
					"graphType": "PX.Objects.IN.INReceiptEntry",
					"primaryView": "receipt"
				}
			]
		}
	]
}