{
	"name": "SO301000_MatrixItems",
	"graphName": null,
	"featureInstalled": [
		"PX.Objects.CS.FeaturesSet+MatrixItem"
	],
	"actions": [],
	"views": [
		{
			"name": "Header",
			"dacClassName": {
				"name": "AddMatrixItemHeader"
			},
			"displayName": "Header",
			"isCollection": false,
			"isFullCollection": false,
			"featureInstalled": [],
			"fields": [
				{
					"args": [
						16
					],
					"stateType": "default",
					"name": "TemplateItemID",
					"bound": true,
					"commitChanges": true,
					"suppressLabel": false,
					"readonly": false,
					"disabled": false,
					"calculated": false,
					"linkCommand": null,
					"text": null,
					"group": null,
					"placeBeforeProperty": null,
					"placeAfterProperty": null,
					"decorators": []
				},
				{
					"args": [
						16
					],
					"stateType": "default",
					"name": "ColAttributeID",
					"bound": true,
					"commitChanges": true,
					"suppressLabel": false,
					"readonly": false,
					"disabled": false,
					"calculated": false,
					"linkCommand": null,
					"text": null,
					"group": null,
					"placeBeforeProperty": null,
					"placeAfterProperty": null,
					"decorators": []
				},
				{
					"args": [
						16
					],
					"stateType": "default",
					"name": "RowAttributeID",
					"bound": true,
					"commitChanges": true,
					"suppressLabel": false,
					"readonly": false,
					"disabled": false,
					"calculated": false,
					"linkCommand": null,
					"text": null,
					"group": null,
					"placeBeforeProperty": null,
					"placeAfterProperty": null,
					"decorators": []
				},
				{
					"args": [
						16
					],
					"stateType": "default",
					"name": "ShowAvailable",
					"bound": true,
					"commitChanges": true,
					"suppressLabel": false,
					"readonly": false,
					"disabled": false,
					"calculated": false,
					"linkCommand": null,
					"text": null,
					"group": null,
					"placeBeforeProperty": null,
					"placeAfterProperty": null,
					"decorators": []
				},
				{
					"args": [
						16
					],
					"stateType": "default",
					"name": "SiteID",
					"bound": true,
					"commitChanges": true,
					"suppressLabel": false,
					"readonly": false,
					"disabled": false,
					"calculated": false,
					"linkCommand": null,
					"text": null,
					"group": null,
					"placeBeforeProperty": null,
					"placeAfterProperty": null,
					"decorators": []
				}
			],
			"extensions": [],
			"decorators": [],
			"actions": []
		},
		{
			"name": "AdditionalAttributes",
			"dacClassName": {
				"name": "MatrixAttributes"
			},
			"displayName": "Add Matrix Item",
			"isCollection": true,
			"isFullCollection": false,
			"featureInstalled": [],
			"fields": [],
			"extensions": [],
			"decorators": [
				{
					"name": {
						"name": "viewInfo"
					},
					"arguments": [
						{
							"containerName": "Add Matrix Item"
						}
					]
				}
			],
			"actions": []
		},
		{
			"name": "Matrix",
			"dacClassName": {
				"name": "EntryMatrix"
			},
			"displayName": "Add Matrix Item",
			"isCollection": true,
			"isFullCollection": false,
			"featureInstalled": [],
			"fields": [],
			"extensions": [],
			"decorators": [
				{
					"name": {
						"name": "viewInfo"
					},
					"arguments": [
						{
							"containerName": "Add Matrix Item"
						}
					]
				}
			],
			"actions": []
		}
	],
	"extensions": [],
	"decorators": [
		{
			"name": {
				"name": "featureInstalled"
			},
			"arguments": [
				"PX.Objects.CS.FeaturesSet+MatrixItem"
			]
		}
	]
}